CHANGELOG.txt
LICENCE.txt
MANIFEST.in
README.txt
setup.py
codes/cache.py
codes/main.py
ormucoq3lrucache.egg-info/PKG-INFO
ormucoq3lrucache.egg-info/SOURCES.txt
ormucoq3lrucache.egg-info/dependency_links.txt
ormucoq3lrucache.egg-info/top_level.txt