Metadata-Version: 1.1
Name: ormucoq3lrucache
Version: 1.0
Summary: A basic lru cache
Home-page: UNKNOWN
Author: Yihe Zhang
Author-email: yihe@msn.com
License: MIT
Keywords: lru
Platform: UNKNOWN
Classifier: Development Status :: 5 - Production/Stable
Classifier: Intended Audience :: Education
Classifier: Operating System :: Microsoft :: Windows :: Windows 10
Classifier: License :: OSI Approved :: MIT License
Classifier: Programming Language :: Python :: 3
